<?xml version="1.0" encoding="utf-8" ?>
<odoo>
    <template id="layout_loader">
        <div class="page-loading visible">
            <div class="page-loading-inn">
                <div class="page-loading-transform">
                    <div class="ux-loading"></div>
                    <div class="ux-loading-transform">
                        <div class="loading-dot1"></div>
                        <div class="loading-dot2"></div>
                    </div>
                </div>
                <img src="/bywatos_website_theme/static/src/img/svg/logo-bw.svg"
                     alt="Logo By Watos"
                     class="page-loading-transform-logo"/>
                <div class="page-loading-transform-text">
                    Design in Lyon
                </div>
            </div>
        </div>
    </template>
</odoo>